Workbook

Sheet ปรับแผนงบลงทุน
A1: ฟอร์มปรับแผนบลงทุนครุภัณฑ์ ประจำปีงบประมาณ 2568
A2: กลุ่มงาน............................................................หน่วยงาน โรงพยาบาลอุตรดิตถ์
A3: ลำดับที่ | B3: ชื่อรายการครุภัณฑ์ที่มิใช่ทางการแพทย์ | C3: รหัสครุภัณฑ์ กบรส | D3: รหัสครุภัณฑ์ | E3: หน่วยนับ | F3: จำนวนที่ขอซื้อ | H3: ราคาต่อหน่วย (บาท) | I3: รวมเงิน (บาท) | J3: ราคากลาง ( กบรส ) | K3: เหตุผลความจำเป็นในการจัดหา (ไม่เกิน 5 บรรทัด) | L3: หน่วยงาน | M3: เลขครุภัณฑ์เดิม | N3: รหัสแหล่งเงิน | O3: รหัสหน่วยงาน
F4: ใหม่ | G4: ทดแทน
B19: รวมทั้งสิ้น | I19: =SUM(I5:I18) -> 0

Sheet วัสดุทั่วไป
B1: ปรับแผนปฏิบัติการจัดซื้อจัดจ้าง ประเภท วัสดุทั่วไป / จ้างเหมาทั่วไป
B2: หน่วยงาน.......................................โรงพยาบาลอุตรดิตถ์ จังหวัด อุตรดิตถ์ รหัสหน่วยงาน 5 หลัก 10673
B3: ประจำปีงบประมาณ พ.ศ. 2569
A5: ลำดับที่ | B5: ลำดับแผน | C5: รายการ | D5: รหัส | E5: ขนาดบรรจุ | F5: ซื้อแล้ว | G5: อัตราการ | H5: คงคลัง | I5: แผนอนุมัติ | J5: แผนจัดซื้อเดิม | M5: แผนจัดซื้อใหม่ | P5: มูลค่าปรับแผน | Q5: มูลค่าปรับแผน | R5: มูลค่าปรับแผน | S5: มูลปรับแผน | T5: เหตุผลการปรับแผน | U5: หน่วยงาน | V5: หมายเหตุ
B6: เดิม | E6: (หน่วยนับ) | F6: เท่าไหร่ | G6: ใช้/ปี | J6: จำนวน (หน่วยนับ) | K6: ราคาต่อหน่วย (บาท) | L6: มูลค่า (บาท) | M6: จำนวน (หน่วยนับ) | N6: ราคาต่อหน่วย (บาท) | O6: มูลค่า (บาท) | P6: บาท | Q6: ครั้งที่2 | R6: ครั้งที่ 1 | S6: สะสม
V7: =VLOOKUP(C7,Sheet3!$1:$1048576,2,) -> #N/A
V8: =VLOOKUP(C8,Sheet3!$1:$1048576,2,) -> #N/A
V9: =VLOOKUP(C9,Sheet3!$1:$1048576,2,) -> #N/A
V10: =VLOOKUP(C10,Sheet3!$1:$1048576,2,) -> #N/A
V11: =VLOOKUP(C11,Sheet3!$1:$1048576,2,) -> #N/A
V12: =VLOOKUP(C12,Sheet3!$1:$1048576,2,) -> #N/A
V13: =VLOOKUP(C13,Sheet3!$1:$1048576,2,) -> #N/A
V14: =VLOOKUP(C14,Sheet3!$1:$1048576,2,) -> #N/A
V15: =VLOOKUP(C15,Sheet3!$1:$1048576,2,) -> #N/A
V16: =VLOOKUP(C16,Sheet3!$1:$1048576,2,) -> #N/A
V17: =VLOOKUP(C17,Sheet3!$1:$1048576,2,) -> #N/A
V18: =VLOOKUP(C18,Sheet3!$1:$1048576,2,) -> #N/A
... V35: =VLOOKUP(C35,Sheet3!$1:$1048576,2,) -> #N/A
C37: รวมทั้งสิ้น | I37: =SUM(I7:I36) -> 0 | L37: =SUM(L7:L36) -> 0 | O37: =SUM(O7:O36) -> 0 | P37: =SUM(P7:P36) -> 0 | Q37: =SUM(Q7:Q36) -> 0 | R37: =SUM(R7:R36) -> 0 | S37: =SUM(S7:S36) -> 0

Sheet Sheet3
A1: item_name | B1: item_id | C1: item_unit | D1: item_type | E1: item_use_status | F1: item_standard_price | G1: item_unit_qty | H1: item_package_name | I1: icode | J1: reorder_level | K1: reorder_qty | L1: standard_code | M1: dummy_left_qty | N1: dummy_left_price | O1: unit_cost | P1: item_sub_unit_qty | Q1: old_unit_cost | R1: oldcode | S1: newcode | T1: default_department_id | U1: fix_department | V1: stock_item_cost_type_id | W1: stock_class_id | X1: barcode_number | Y1: unit_price | Z1: item_code | AA1: hos_guid | AB1: gpo_code | AC1: didstd_code | AD1: avg_month_use_qty | AE1: item_regno | AF1: bdg_nextyear_percent | AG1: stock_item_regdate | AH1: item_note | AI1: safety_stock | AJ1: onhand_qty | AK1: avg_lead_day | AL1: last_active_date | AM1: gpo_vmi | AN1: balance_qty | AO1: item_eng | AP1: item_trand | AQ1: item_type_group | AR1: item_status_control | AS1: item_van_type | AT1: search_keyword | AU1: abc | AV1: ved_code | AW1: pharmacology_group1 | AX1: pharmacology_group2 | AY1: pharmacology_group3 | AZ1: last_po_date | BA1: item_common_name | BB1: stock_item_mtr_id | BC1: stock_item_acct_id | BD1: stock_sub_class_id | BE1: item_trade_name | BF1: stock_item_note | BG1: last_po_price | BH1: stock_item_std_price | BI1: stock_item_ref_price | BJ1: vat_percent | BK1: expire_qty | BL1: supplier_list_text | BM1: vendor_list_text | BN1: po_wait_qty | BO1: last_deliver_date | BP1: item_min_qty | BQ1: item_max_qty | BR1: last_po_price_1 | BS1: sap_unit_name | BT1: sap_item_name | BU1: sap_unit_cost | BV1: sap_active | BW1: manufacturer_list_text | BX1: use_fixed_avg_cost | BY1: fixed_avg_cost | BZ1: stock_mrp_order_type_id | CA1: stock_mrp_lot_size | CB1: last_stock_vendor_id | CC1: stock_item_ed_type_id | CD1: last_calc_si_map | CE1: apply_vat | CF1: update_datetime | CG1: drugitems_no_substock | CH1: gpsc_code | CI1: item_color | CJ1: ttmt_code
A2: T locking plate | B2: 11590 | C2: ชิ้น | D2: 26 | E2: Y | O2: 0 | V2: 1 | W2: 13 | Z2: 004-02-160-018 | AG2: 45865 | BA2: T locking plate | BC2: 6 | BE2: T locking plate | CG2: Y
A3: [ปิดใช้งาน]กระดาษ A4 ขนาด 80 แกรม | B3: 3153 | C3: รีม | D3: 11 | E3: N | O3: 120 | V3: 1 | Y3: 149 | Z3: PI-0010350415 | AG3: 45865 | AJ3: 0 | BA3: กระดาษ A4 ขนาด 80 แกรม | BB3: 1 | BC3: 12 | BE3: กระดาษ A4 ขนาด 80 แกรม | BK3: 0 | BL3: บริษัท ศรีพงษ์กรุ๊ป มาร์เก็ตติ้ง จำกัด | BM3: บริษัท ศรีพงษ์กรุ๊ป มาร์เก็ตติ้ง จำกัด | BN3: 0 | CD3: 2025-08-13 08:48:10.980075 | CF3: 45882.702 | CG3: Y
A4: Hepatitis B immunoglobulin-180 iu/ml-1ml (HBIG)=IMMUNO HBS | B4: 8529 | C4: ขวด | D4: 1 | E4: Y | J4: 9 | K4: 20 | O4: 2457.3034 | R4: 1001368 | V4: 1 | W4: 52 | Y4: 2764 | Z4: B150100-020 | AG4: 45865 | AJ4: 0 | AL4: 45901 | AU4: C | AZ4: 45840 | BA4: Hepatitis B immunoglobulin-180 iu/ml-1ml | BB4: 1 | BC4: 4 | BD4: 6 | BE4: HBIG 180 U/ml-1ml#inj | BF4: เมื่อยาหมดแล้ว เปลี่ยนไปซื้อ 200 IU/ml ศูนย์บริการโลหิตแห่งชาติ สภากาชาดไทย รหัส B150100-002 ราคา 1500/ขวด (ยกเว้นภาษีมูลค่าเพิ่ม) | BG4: 2700 | BK4: 0 | BL4: บริษัท ไบโอจีนีเทค จำกัด | BM4: บริษัท ไบโอจีนีเทค จำกัด | BN4: 0 | BO4: 45901 | BP4: 6 | BQ4: 29 | BR4: 2700 | CB4: 589 | CC4: 1 | CD4: 2025-12-26 13:56:56.749386 | CF4: 45952.667 | CG4: N | CH4: 99000051201600
A5: Mixter clamps 28 cms. | B5: 13094 | C5: ชิ้น | D5: 26 | E5: Y | V5: 1 | W5: 17 | Z5: OR04-05-001-004 | AG5: 45865 | BA5: Mixter clamps 28 cms. | BB5: 1 | BC5: 6 | BE5: Mixter clamps 28 cms. | CF5: 45999.648 | CG5: Y
A6: จ้างเหมาทำป้ายพร้อมขาตั้ง | B6: 14111 | C6: ชุด | D6: 57 | E6: Y | AG6: 45972 | BA6: จ้างเหมาทำป้ายพร้อมขาตั้ง | BB6: 1 | BC6: 57 | BE6: จ้างเหมาทำป้ายพร้อมขาตั้ง | CF6: 45972.362 | CG6: Y
A7: Tap 0.4-4.0 mm cancelous (thread) | B7: 11593 | C7: ชิ้น | D7: 26 | E7: Y | O7: 2450 | V7: 1 | W7: 13 | Z7: 004-02-179-003 | AG7: 45865 | BA7: Tap 0.4-4.0 mm cancelous (thread) | BC7: 6 | BE7: Tap 0.4-4.0 mm cancelous (thread) | CG7: Y
A8: Tapered 1.5x11.1 mm for midas Rex | B8: 11596 | C8: ชิ้น | D8: 26 | E8: Y | O8: 4500 | V8: 1 | W8: 11 | Z8: 004-06-166-009 | AG8: 45865 | BA8: Tapered 1.5x11.1 mm for midas Rex | BC8: 6 | BE8: Tapered 1.5x11.1 mm for midas Rex | CG8: Y
A9: Tapered 2.3x16.4 mm for midas Rex | B9: 11597 | C9: ชิ้น | D9: 26 | E9: Y | O9: 4500 | V9: 1 | W9: 11 | Z9: 004-06-166-008 | AG9: 45865 | BA9: Tapered 2.3x16.4 mm for midas Rex | BC9: 6 | BE9: Tapered 2.3x16.4 mm for midas Rex | CG9: Y
A10: Taylor spinal retractor | B10: 11599 | C10: ชิ้น | D10: 26 | E10: Y | O10: 4500 | V10: 1 | W10: 13 | Z10: OR02-10-001-001 | AG10: 45865 | BA10: Taylor spinal retractor | BC10: 6 | BE10: Taylor spinal retractor | CG10: Y
A11: Pear shape diamond 808/014 | B11: 463 | C11: ตัว | D11: 14 | E11: Y | O11: 85 | V11: 1 | Y11: 103 | Z11: DM-01-E1-0020 | AG11: 45865 | AJ11: 0 | BA11: Pear shape diamond 808/014 | BC11: 9 | BE11: Pear shape diamond 808/014 | BK11: 0 | BN11: 0 | CD11: 2025-12-22 18:16:40.058241 | CG11: Y
A12: Surgical needle cutting edge 3/8 curve 32 mm. | B12: 11557 | C12: ชิ้น | D12: 26 | E12: Y | O12: 16.66667 | V12: 1 | W12: 9 | Z12: 004-14-002-003 | AG12: 45865 | BA12: Surgical needle cutting edge 3/8 curve 32 mm. | BC12: 6 | BE12: Surgical needle cutting edge 3/8 curve 32 mm. | CG12: Y
A13: Pear shape diamond 808/012 | B13: 462 | C13: ตัว | D13: 14 | E13: Y | O13: 85 | V13: 1 | Y13: 103 | Z13: DM-01-E1-0019 | AG13: 45865 | AJ13: 0 | BA13: Pear shape diamond 808/012 | BC13: 9 | BE13: Pear shape diamond 808/012 | BK13: 0 | BN13: 0 | CD13: 2025-12-22 18:16:39.978186 | CG13: Y
A14: Tibia proximal medial locking5.0 Rt. 9h. | B14: 11625 | C14: ชิ้น | D14: 26 | E14: Y | O14: 11500 | V14: 1 | W14: 13 | Z14: 004-02-171-006 | AG14: 45865 | BA14: Tibia proximal medial locking5.0 Rt. 9h. | BC14: 6 | BE14: Tibia proximal medial locking5.0 Rt. 9h. | CG14: Y
A15: Paperpoint No.SS | B15: 455 | C15: กล่อง | D15: 14 | E15: Y | O15: 60 | V15: 1 | Y15: 73 | Z15: DM-01-C2-0001 | AG15: 45865 | AJ15: 5 | BA15: Paperpoint No.SS | BC15: 9 | BE15: Paperpoint No.SS | BK15: 0 | BN15: 0 | CD15: 2025-12-22 18:16:39.33668 | CG15: Y
A16: Fuji IX capsule | B16: 230 | C16: กล่อง | D16: 14 | E16: Y | O16: 2000 | V16: 1 | Y16: 2261 | Z16: DM-01-B1-0020 | AG16: 45865 | AJ16: 1 | BA16: Fuji IX capsule | BC16: 9 | BE16: Fuji IX capsule | BK16: 0 | BN16: 0 | CD16: 2025-12-22 18:16:39.207209 | CG16: Y
A17: Tubbing occlusion clamps 20 cms. | B17: 13092 | C17: ชิ้น | D17: 26 | E17: Y | V17: 1 | Z17: OR12-07-001-002 | AG17: 45865 | BA17: Tubbing occlusion clamps 20 cms. | BC17: 6 | BE17: Tubbing occlusion clamps 20 cms. | CG17: Y
A18: Round diamond 801/023 | B18: 522 | C18: ตัว | D18: 14 | E18: Y | O18: 95 | V18: 1 | Y18: 115 | Z18: DM-01-E1-0009 | AG18: 45865 | AJ18: 0 | BA18: Round diamond 801/023 | BC18: 9 | BE18: Round diamond 801/023 | BK18: 0 | BN18: 0 | CD18: 2025-12-22 18:16:40.000186 | CG18: Y
A19: Microbrush | B19: 397 | C19: กล่อง | D19: 14 | E19: Y | O19: 120 | V19: 1 | Y19: 149 | Z19: DM-01-C1-0126 | AG19: 45865 | AJ19: 0 | BA19: Microbrush | BC19: 9 | BE19: Microbrush | BK19: 0 | BN19: 0 | CD19: 2025-12-22 18:16:39.808222 | CG19: Y
A20: Self etching bonding | B20: 549 | C20: ชุด | D20: 14 | E20: Y | O20: 3317 | V20: 1 | Y20: 3710 | Z20: DM-01-C1-0026 | AG20: 45865 | AJ20: 0 | BA20: Self etching bonding | BC20: 9 | BE20: Self etching bonding | BK20: 0 | BN20: 0 | CD20: 46013.762 | CG20: Y
A21: 661 HP ขาว | B21: 2 | C21: ตัว | D21: 14 | E21: Y | O21: 95 | V21: 1 | Y21: 115 | Z21: DM-01-E4-0009 | AG21: 45865 | AJ21: 0 | AL21: 45875 | AZ21: 45846 | BA21: 661 HP ขาว | BC21: 9 | BE21: 661 HP ขาว | BG21: 95 | BK21: 0 | BN21: 0 | BO21: 45875 | BR21: 95 | CB21: 422 | CD21: 2025-12-22 18:15:38.252226 | CG21: Y
A22: เมนเบรคเกอร์ 50A | B22: 5681 | C22: ตัว | D22: 10 | E22: Y | O22: 880 | V22: 1 | Y22: 1023 | Z22: PI-0030220004 | AG22: 45865 | AJ22: 0 | AL22: 45918 | AZ22: 45887 | BA22: เมนเบรคเกอร์ 50A | BC22: 15 | BE22: เมนเบรคเกอร์ 50A | BG22: 880 | BK22: 0 | BN22: 0 | BO22: 45918 | BR22: 880 | CB22: 1755 | CD22: 2025-12-22 18:17:27.57572 | CG22: Y
A23: Round diamond 801/014 | B23: 518 | C23: ตัว | D23: 14 | E23: Y | O23: 95 | V23: 1 | Y23: 115 | Z23: DM-01-E1-0005 | AG23: 45865 | AJ23: 40 | AL23: 45875 | AZ23: 45846 | BA23: Round diamond 801/014 | BC23: 9 | BE23: Round diamond 801/014 | BG23: 95 | BK23: 0 | BN23: 0 | BO23: 45875 | BR23: 95 | CB23: 422 | CD23: 2025-12-22 18:15:38.425738 | CG23: Y
A24: Hemoclip large(สีส้ม) | B24: 10717 | C24: ตัว | D24: 26 | E24: Y | O24: 47.33307 | V24: 1 | W24: 6 | Y24: 58 | Z24: 004-06-035-003 | AG24: 45865 | AJ24: 300 | AL24: 45875 | AZ24: 45867 | BA24: Hemoclip large(สีส้ม) | BB24: 1 | BC24: 6 | BE24: Hemoclip large(สีส้ม) | BF24: 180 ตัว /กล่อง | BG24: 7100 | BK24: 0 | BN24: 0 | BO24: 45875 | BR24: 59.167 | CB24: 335 | CD24: 2025-12-22 18:16:14.035285 | CF24: 45988.536 | CG24: Y
A25: Round diamond 801 คาดแดง | B25: 513 | C25: ตัว | D25: 14 | E25: Y | O25: 95 | V25: 1 | Y25: 115 | Z25: DM-01-E1-0011 | AG25: 45865 | AJ25: 0 | BA25: Round diamond 801 คาดแดง | BC25: 9 | BE25: Round diamond 801 คาดแดง | BK25: 0 | BN25: 0 | CD25: 2025-12-22 18:16:40.015178 | CG25: Y
A26: Wax knife | B26: 762 | C26: อัน | D26: 14 | E26: Y | O26: 110 | V26: 1 | Y26: 138 | Z26: DM-01-G2-0006 | AG26: 45865 | AJ26: 0 | AL26: 45894 | AZ26: 45846 | BA26: Wax knife | BC26: 9 | BE26: Wax knife | BG26: 110 | BK26: 0 | BN26: 0 | BO26: 45894 | BR26: 110 | CB26: 1062 | CD26: 2025-12-22 18:17:45.837272 | CG26: Y
A27: Suture holding insert | B27: 13095 | C27: ชิ้น | D27: 26 | E27: Y | O27: 13095 | V27: 1 | Y27: 14466 | Z27: 004-12-025-003 | AG27: 45865 | BA27: Suture holding insert | BB27: 1 | BC27: 6 | BE27: Suture holding insert | BR27: 0 | CF27: 45959.615 | CG27: N
A28: Variable screw stainless steel 3.5 mm -shaft | B28: 13116 | C28: ชิ้น | D28: 26 | E28: Y | O28: 1600 | V28: 1 | W28: 13 | Y28: 1821 | Z28: 004-02-128-334 | AG28: 45865 | BA28: Variable screw stainless steel 3.5 mm -shaft | BB28: 1 | BC28: 6 | BE28: Variable screw stainless steel 3.5 mm -shaft | BI28: 1600 | BR28: 0 | CF28: 45950.427 | CG28: N
A29: LCP stainless steel 2.7/3.5 mm. | B29: 13133 | C29: ชิ้น | D29: 26 | E29: Y | O29: 17000 | V29: 1 | W29: 13 | Y29: 18761 | Z29: 004-02-172-013 | AG29: 45865 | BA29: LCP stainless steel 2.7/3.5 mm. | BB29: 1 | BC29: 6 | BE29: LCP stainless steel 2.7/3.5 mm. | BR29: 0 | CF29: 45988.529 | CG29: Y
A30: 2.7/3.5 Fibula Specific LCP | B30: 13129 | C30: ชิ้น | D30: 26 | E30: Y | O30: 18000 | V30: 1 | W30: 13 | Y30: 19861 | Z30: 004-02-165-013 | AG30: 45865 | BA30: 2.7/3.5 Fibula Specific LCP | BB30: 1 | BC30: 6 | BE30: 2.7/3.5 Fibula Specific LCP | BR30: 0 | CF30: 45950.667 | CG30: N
A31: locking srcrew Ti 3.5 mm Pilon | B31: 13124 | C31: ชิ้น | D31: 26 | E31: Y | O31: 2140 | V31: 1 | W31: 13 | Y31: 2415 | Z31: 004-02-128-343 | AG31: 45865 | BA31: locking srcrew Ti 3.5 mm Pilon | BB31: 1 | BC31: 6 | BE31: locking srcrew Ti 3.5 mm Pilon | BR31: 0 | CF31: 45950.668 | CG31: N
A32: Locking-screw Ti 2.7 mm. Conical | B32: 13120 | C32: ชิ้น | D32: 26 | E32: Y | O32: 1000 | V32: 1 | W32: 13 | Y32: 1161 | Z32: 004-02-128-339 | AG32: 45865 | BA32: Locking-screw Ti 2.7 mm. Conical | BB32: 1 | BC32: 6 | BE32: Locking-screw Ti 2.7 mm. Conical | BR32: 0 | CF32: 45950.591 | CG32: N
A33: Waterproof Clear Bandage (พลาสเตอร์ใสกันน้ำปราศจากเชื้อ) | B33: 5082 | C33: ชิ้น | D33: 4 | E33: Y | J33: 3000 | K33: 4500 | O33: 0.83462 | V33: 1 | W33: 70 | Y33: 1.5 | Z33: MS-04-VJ-0001 | AG33: 45865 | AJ33: 3900 | AL33: 45944 | AZ33: 45917 | BA33: Waterproof Clear Bandage (พลาสเตอร์ใสกันน้ำปราศจากเชื้อ) | BB33: 1 | BC33: 6 | BE33: Waterproof Clear Bandage (พลาสเตอร์ใสกันน้ำปราศจากเชื้อ) | BG33: 83.46 | BK33: 0 | BL33: บริษัท ซิลลิค ฟาร์มา จำกัด | BM33: บริษัท ซิลลิค ฟาร์มา จำกัด | BN33: 0 | BO33: 45944 | BP33: 3000 | BQ33: 7500 | BR33: 0.835 | CB33: 345 | CD33: 2026-01-05 13:13:54.266048 | CF33: 45860.758 | CG33: Y
A34: Variable screw stainless steel 3.5 mm | B34: 13114 | C34: ชิ้น | D34: 26 | E34: Y | O34: 2000 | V34: 1 | W34: 13 | Y34: 2261 | Z34: 004-02-128-332 | AG34: 45865 | BA34: Variable screw stainless steel 3.5 mm | BB34: 1 | BC34: 6 | BE34: Variable screw stainless steel 3.5 mm | BR34: 0 | CF34: 45950.426 | CG34: N
A35: 3.5 Locking screw St. | B35: 13119 | C35: ชิ้น | D35: 26 | E35: Y | O35: 1600 | V35: 1 | W35: 13 | Y35: 1821 | Z35: 004-02-128-338 | AG35: 45865 | BA35: 3.5 Locking screw St. | BB35: 1 | BC35: 6 | BE35: 3.5 Locking screw St. | BR35: 0 | CF35: 45968.654 | CG35: N
A36: Fine Blade SM64 | B36: 13090 | C36: ชิ้น | D36: 26 | E36: Y | O36: 8560 | V36: 1 | W36: 13 | Y36: 9477 | Z36: 004-02-092-016 | AG36: 45865 | BA36: Fine Blade SM64 | BB36: 1 | BC36: 6 | BE36: Fine Blade SM64 | BR36: 0 | CF36: 45951.59 | CG36: Y
A37: Variable screw stainless steel 2.7 mm | B37: 13115 | C37: ชิ้น | D37: 26 | E37: Y | O37: 2000 | V37: 1 | W37: 13 | Y37: 2261 | Z37: 004-02-128-333 | AG37: 45865 | BA37: Variable screw stainless steel 2.7 mm | BB37: 1 | BC37: 6 | BE37: Variable screw stainless steel 2.7 mm | BR37: 0 | CF37: 45950.426 | CG37: N
A38: Cannultaed screw 3.7/5.0 mm | B38: 13108 | C38: ชิ้น | D38: 26 | E38: Y | O38: 2500 | V38: 1 | W38: 13 | Y38: 2811 | Z38: 004-02-114-042 | AG38: 45865 | BA38: Cannultaed screw 3.7/5.0 mm | BB38: 1 | BC38: 6 | BE38: Cannultaed screw 3.7/5.0 mm | BR38: 0 | CF38: 45994.492 | CG38: Y
A39: locking srcrew Ti 2.7 mm Pilon | B39: 13125 | C39: ชิ้น | D39: 26 | E39: Y | O39: 2140 | V39: 1 | W39: 13 | Y39: 2415 | Z39: 004-02-128-344 | AG39: 45865 | BA39: locking srcrew Ti 2.7 mm Pilon | BB39: 1 | BC39: 6 | BE39: locking srcrew Ti 2.7 mm Pilon | BR39: 0 | CF39: 45951.431 | CG39: N
A40: LCP Fx around knee 5.0 mm. | B40: 13136 | C40: ชิ้น | D40: 26 | E40: Y | O40: 17000 | V40: 1 | W40: 13 | Y40: 18761 | Z40: 004-02-172-016 | AG40: 45865 | BA40: LCP Fx around knee 5.0 mm. | BB40: 1 | BC40: 6 | BE40: LCP Fx around knee 5.0 mm. | BR40: 0 | CF40: 45999.711 | CG40: Y
A41: locking srcrew Ti 3.5 mm Foot ankle | B41: 13126 | C41: ชิ้น | D41: 26 | E41: Y | O41: 1400 | V41: 1 | W41: 13 | Y41: 1601 | Z41: 004-02-128-345 | AG41: 45865 | BA41: locking srcrew Ti 3.5 mm Foot ankle | BB41: 1 | BC41: 6 | BE41: locking srcrew Ti 3.5 mm Foot ankle | BR41: 0 | CF41: 45951.437 | CG41: N
A42: locking srcrew Ti 2.7mm Foot ankle | B42: 13127 | C42: ชิ้น | D42: 26 | E42: Y | O42: 1400 | V42: 1 | W42: 13 | Y42: 1601 | Z42: 004-02-128-346 | AG42: 45865 | BA42: locking srcrew Ti 2.7mm Foot ankle | BB42: 1 | BC42: 6 | BE42: locking srcrew Ti 2.7mm Foot ankle | BR42: 0 | CF42: 45951.438 | CG42: N
A43: Tiemann catheter 14 Fr. | B43: 11634 | C43: ชิ้น | D43: 26 | E43: Y | O43: 110 | V43: 1 | W43: 16 | Z43: 004-09-007-003 | AG43: 45865 | BA43: Tiemann catheter 14 Fr. | BC43: 6 | BE43: Tiemann catheter 14 Fr. | CG43: Y
A44: Locking-screw stainless steel 2.7 mm. | B44: 13117 | C44: ชิ้น | D44: 26 | E44: Y | O44: 2000 | V44: 1 | W44: 13 | Y44: 2261 | Z44: 004-02-128-335 | AG44: 45865 | BA44: Locking-screw stainless steel 2.7 mm. | BB44: 1 | BC44: 6 | BE44: Locking-screw stainless steel 2.7 mm. | BR44: 0 | CF44: 45950.429 | CG44: N
A45: Locking-screw stainless steel 5.0 mm. | B45: 13118 | C45: ชิ้น | D45: 26 | E45: Y | O45: 1600 | V45: 1 | W45: 13 | Y45: 1821 | Z45: 004-02-128-337 | AG45: 45865 | BA45: Locking-screw stainless steel 5.0 mm. | BB45: 1 | BC45: 6 | BE45: Locking-screw stainless steel 5.0 mm. | BR45: 0 | CF45: 45950.458 | CG45: N
A46: Locking-screw Ti 3.5 mm. Conical | B46: 13121 | C46: ชิ้น | D46: 26 | E46: Y | O46: 1000 | V46: 1 | W46: 13 | Y46: 1161 | Z46: 004-02-128-340 | AG46: 45865 | BA46: Locking-screw Ti 3.5 mm. Conical | BB46: 1 | BC46: 6 | BE46: Locking-screw Ti 3.5 mm. Conical | BR46: 0 | CF46: 45950.591 | CG46: N
A47: Tiemann catheter 16 Fr. | B47: 11635 | C47: ชิ้น | D47: 26 | E47: Y | O47: 80 | V47: 1 | W47: 16 | Z47: 004-09-007-004 | AG47: 45865 | BA47: Tiemann catheter 16 Fr. | BC47: 6 | BE47: Tiemann catheter 16 Fr. | CG47: Y
A48: Conical-screw Ti 3.5 mm. | B48: 13123 | C48: ชิ้น | D48: 26 | E48: Y | O48: 850 | V48: 1 | W48: 13 | Y48: 989 | Z48: 004-02-128-342 | AG48: 45865 | BA48: Conical-screw Ti 3.5 mm. | BB48: 1 | BC48: 6 | BE48: Conical-screw Ti 3.5 mm. | BR48: 0 | CF48: 45950.603 | CG48: Y
A49: Cortex screw 3.5mm Conical | B49: 13106 | C49: ชิ้น | D49: 26 | E49: Y | O49: 300 | V49: 1 | W49: 13 | Y49: 356 | Z49: 004-02-003-038 | AG49: 45865 | BA49: Cortex screw 3.5mm Conical | BB49: 1 | BC49: 6 | BE49: Cortex screw 3.5mm Conical | BR49: 0 | CF49: 45950.604 | CG49: N
A50: WEDGE BURRS | B50: 13089 | C50: ชิ้น | D50: 26 | E50: Y | O50: 8560 | V50: 1 | W50: 13 | Y50: 9477 | Z50: 004-02-092-015 | AG50: 45865 | BA50: WEDGE BURRS | BB50: 1 | BC50: 6 | BE50: WEDGE BURRS | BR50: 0 | CF50: 45951.591 | CG50: Y
A51: Locking-screw Ti 3.5 mm. Philos | B51: 13128 | C51: ชิ้น | D51: 26 | E51: Y | O51: 1000 | V51: 1 | W51: 13 | Y51: 1161 | Z51: 004-02-150-009 | AG51: 45865 | BA51: Locking-screw Ti 3.5 mm. Philos | BB51: 1 | BC51: 6 | BE51: Locking-screw Ti 3.5 mm. Philos | BR51: 0 | CF51: 45950.625 | CG51: Y
A52: SHANNON BURRS | B52: 13088 | C52: ชิ้น | D52: 26 | E52: Y | O52: 8560 | V52: 1 | W52: 13 | Y52: 9477 | Z52: 004-02-092-014 | AG52: 45865 | BA52: SHANNON BURRS | BB52: 1 | BC52: 6 | BE52: SHANNON BURRS | BR52: 0 | CF52: 45951.592 | CG52: Y
A53: CUTTER BURR 2.0-5.1/ 8-15mm | B53: 13087 | C53: ชิ้น | D53: 26 | E53: Y | O53: 8560 | V53: 1 | W53: 13 | Y53: 9477 | Z53: 004-02-092-013 | AG53: 45865 | BA53: CUTTER BURR 2.0-5.1/ 8-15mm | BB53: 1 | BC53: 6 | BE53: CUTTER BURR 2.0-5.1/ 8-15mm | BR53: 0 | CF53: 45951.592 | CG53: Y
A54: Cannulated screw 3.0/4.0 | B54: 13111 | C54: ชิ้น | D54: 26 | E54: Y | O54: 5000 | V54: 1 | W54: 13 | Y54: 5561 | Z54: 004-02-114-045 | AG54: 45865 | BA54: Cannulated screw 3.0/4.0 | BB54: 1 | BC54: 6 | BE54: Cannulated screw 3.0/4.0 | BR54: 0 | CF54: 45951.595 | CG54: Y
A55: MIS Canulated screw 7.0mm, 60-160 mm | B55: 13110 | C55: ชิ้น | D55: 26 | E55: Y | O55: 6420 | V55: 1 | W55: 13 | Y55: 7123 | Z55: 004-02-114-044 | AG55: 45865 | BA55: MIS Canulated screw 7.0mm, 60-160 mm | BB55: 1 | BC55: 6 | BE55: MIS Canulated screw 7.0mm, 60-160 mm | BR55: 0 | CF55: 45951.596 | CG55: Y
A56: MIS Canulated screw 3.0-4.0mm, 16-60 mm | B56: 13109 | C56: ชิ้น | D56: 26 | E56: Y | O56: 6420 | V56: 1 | W56: 13 | Y56: 7123 | Z56: 004-02-114-043 | AG56: 45865 | BA56: MIS Canulated screw 3.0-4.0mm, 16-60 mm | BB56: 1 | BC56: 6 | BE56: MIS Canulated screw 3.0-4.0mm, 16-60 mm | BR56: 0 | CF56: 45951.597 | CG56: Y
A57: Cortex screw 3.5x26 mm. | B57: 10288 | C57: ชิ้น | D57: 26 | E57: Y | O57: 105 | V57: 1 | W57: 13 | Y57: 132 | Z57: 004-02-003-009 | AG57: 45865 | AJ57: 70 | BA57: Cortex screw 3.5x26 mm. | BC57: 6 | BE57: Cortex screw 3.5x26 mm. | BF57: 1. วัตถุประสงค์การใช้งาน เป็นสกรูสำหรับยึดตรึงกระดูกแข็ง โดยใช้ร่วมกับ plate เพื่อดามกระดูกทั่วไปทางด้านศัลยกรรมกระดูกและข้อ 2. คุณลักษณะในทางเทคนิค 2.1 สกรูทำด้วยโลหะปลอดสนิม (stainless steel) 2.2 เป็นสกรูชนิด non-self tapping ขนาดเส้นผ่าศูนย์กลาง 3.5 มิลลิเมตร 2.3 ลักษณะหัวสกรูเป็นแบบหกเหลี่ยม 2.4 มีความยาวตั้งแต่ 10 มิลลิเมตร ถึง 60 มิลลิเมตร 3. เงื่อนไขเฉพาะ 3.1 เป็นสินค้าที่ไม่เคยผ่านการใช้งานมาก่อน 3.2 เป็นผลิตภัณฑ์ได้รับรองมาตรฐานสากล ISO 3.3 สามารถทำให้ปราศจากเชื้อได้โดยการอบด้วยไอน้ำแรงดันสูงโดยที่โลหะไม่เสื่อมสภาพ | BK57: 0 | BN57: 0 | CD57: 2025-12-22 18:16:27.479277 | CG57: Y
A58: Broad LCP Stainless steel 5.0 | B58: 13138 | C58: ชิ้น | D58: 26 | E58: Y | O58: 9000 | V58: 1 | W58: 13 | Y58: 9961 | Z58: 004-02-176-021 | AG58: 45865 | BA58: Broad LCP Stainless steel 5.0 | BB58: 1 | BC58: 6 | BE58: Broad LCP Stainless steel 5.0 | BR58: 0 | CF58: 45988.529 | CG58: Y
A59: LCP stainless steel 3.5 mm. | B59: 13134 | C59: ชิ้น | D59: 26 | E59: Y | O59: 17000 | V59: 1 | W59: 13 | Y59: 18761 | Z59: 004-02-172-014 | AG59: 45865 | BA59: LCP stainless steel 3.5 mm. | BB59: 1 | BC59: 6 | BE59: LCP stainless steel 3.5 mm. | BR59: 0 | CF59: 45988.529 | CG59: Y
A60: Cranioplasty 3D Titanium (1008) | B60: 13141 | C60: ชุด | D60: 26 | E60: Y | O60: 26000 | V60: 1 | W60: 11 | Y60: 28661 | Z60: 004-06-017-004 | AG60: 45865 | BA60: Cranioplasty 3D Titanium (1008) | BB60: 1 | BC60: 6 | BE60: Cranioplasty 3D Titanium (1008) | BR60: 0 | CF60: 45988.535 | CG60: N
A61: LCP metahyseal Stainless steel 3.5/5.0 mm | B61: 13135 | C61: ชิ้น | D61: 26 | E61: Y | O61: 17000 | V61: 1 | W61: 13 | Y61: 18761 | Z61: 004-02-172-015 | AG61: 45865 | BA61: LCP metahyseal Stainless steel 3.5/5.0 mm | BB61: 1 | BC61: 6 | BE61: LCP metahyseal Stainless steel 3.5/5.0 mm | BR61: 0 | CF61: 45988.529 | CG61: Y
A62: C-Mesh (70 mm.) | B62: 13144 | C62: ชิ้น | D62: 26 | E62: Y | O62: 10000 | V62: 1 | W62: 11 | Z62: 004-06-164-007 | AG62: 45865 | BA62: C-Mesh (70 mm.) | BB62: 1 | BC62: 6 | BE62: C-Mesh (70 mm.) | CF62: 45988.538 | CG62: Y
A63: 5.0 mm Variable Proximal Tibia LCP | B63: 13137 | C63: ชิ้น | D63: 26 | E63: Y | O63: 14000 | V63: 1 | W63: 13 | Y63: 15461 | Z63: 004-02-172-017 | AG63: 45865 | BA63: 5.0 mm Variable Proximal Tibia LCP | BB63: 1 | BC63: 6 | BE63: 5.0 mm Variable Proximal Tibia LCP | BR63: 0 | CF63: 45950.628 | CG63: Y
A64: Flexible ETT cuff No.5.5. | B64: 12288 | C64: อัน | D64: 4 | E64: Y | O64: 0 | V64: 1 | W64: 36 | Z64: MS-ME-06-0059 | AG64: 45865 | BA64: Flexible ETT cuff No.5.5. | BC64: 6 | BE64: Flexible ETT cuff No.5.5. | CG64: Y
A65: Variable LCP stainless steel 2.7/3.5 mm. | B65: 13132 | C65: ชิ้น | D65: 26 | E65: Y | O65: 18000 | V65: 1 | Y65: 19861 | Z65: 004-02-172-012 | AG65: 45865 | BA65: Variable LCP stainless steel 2.7/3.5 mm. | BB65: 1 | BC65: 6 | BE65: Variable LCP stainless steel 2.7/3.5 mm. | BR65: 0 | CF65: 45950.425 | CG65: Y
A66: 2.7/3.5 mm postero lateral distal tibia LCP | B66: 13130 | C66: ชิ้น | D66: 26 | E66: Y | O66: 19260 | V66: 1 | W66: 13 | Y66: 21247 | Z66: 004-02-169-020 | AG66: 45865 | BA66: 2.7/3.5 mm postero lateral distal tibia LCP | BB66: 1 | BC66: 6 | BE66: 2.7/3.5 mm postero lateral distal tibia LCP | BR66: 0 | CF66: 45951.427 | CG66: N
A67: L-Mesh (100 mm.) | B67: 13145 | C67: ชิ้น | D67: 26 | E67: Y | O67: 15000 | V67: 1 | W67: 11 | Y67: 16561 | Z67: 004-06-165-010 | AG67: 45865 | BA67: L-Mesh (100 mm.) | BB67: 1 | BC67: 6 | BE67: L-Mesh (100 mm.) | BR67: 0 | CF67: 45988.539 | CG67: N
A68: Tiemann catheter 18 Fr. | B68: 11636 | C68: ชิ้น | D68: 26 | E68: Y | O68: 110 | V68: 1 | W68: 16 | Z68: 004-09-007-005 | AG68: 45865 | BA68: Tiemann catheter 18 Fr. | BC68: 6 | BE68: Tiemann catheter 18 Fr. | CG68: Y
A69: Tiemann catheter 20 Fr. | B69: 11637 | C69: ชิ้น | D69: 26 | E69: Y | O69: 110 | V69: 1 | W69: 16 | Z69: 004-09-007-006 | AG69: 45865 | BA69: Tiemann catheter 20 Fr. | BC69: 6 | BE69: Tiemann catheter 20 Fr. | CG69: Y
A70: Cranioplasty 3D PMMA (1007) | B70: 13140 | C70: ชุด | D70: 26 | E70: Y | O70: 24000 | V70: 1 | W70: 11 | Y70: 26461 | Z70: 004-06-017-003 | AG70: 45865 | BA70: Cranioplasty 3D PMMA (1007) | BB70: 1 | BC70: 6 | BE70: Cranioplasty 3D PMMA (1007) | BR70: 0 | CF70: 45910.583 | CG70: N
A71: flexible ETT cuff no 8.0. | B71: 12287 | C71: อัน | D71: 4 | E71: Y | O71: 0 | V71: 1 | W71: 36 | Z71: MS-ME-06-0064 | AG71: 45865 | BA71: flexible ETT cuff no 8.0. | BC71: 6 | BE71: flexible ETT cuff no 8.0. | CG71: Y
A72: Flexible ETT uncuff No.4.5. | B72: 12292 | C72: อัน | D72: 4 | E72: Y | O72: 0 | V72: 1 | W72: 36 | Z72: MS-ME-06-0050 | AG72: 45865 | BA72: Flexible ETT uncuff No.4.5. | BC72: 6 | BE72: Flexible ETT uncuff No.4.5. | CG72: Y
A73: Flexible ETT uncuff No.5.0. | B73: 12293 | C73: อัน | D73: 4 | E73: Y | O73: 0 | V73: 1 | W73: 36 | Z73: MS-ME-06-0051 | AG73: 45865 | BA73: Flexible ETT uncuff No.5.0. | BC73: 6 | BE73: Flexible ETT uncuff No.5.0. | CG73: Y
A74: มอลโตเดร็กซ์ตรินสูตรเบาหวาน. | B74: 4566 | C74: กระป๋อง | D74: 18 | E74: Y | O74: 193 | V74: 1 | W74: 80 | Z74: PI-0060010015 | AG74: 45865 | BA74: มอลโตเดร็กซ์ตรินสูตรเบาหวาน. | BC74: 10 | BE74: มอลโตเดร็กซ์ตรินสูตรเบาหวาน. | BL74: บริษัท มัณฑนา มาร์เก็ตติ้ง จำกัด | BM74: บริษัท มัณฑนา มาร์เก็ตติ้ง จำกัด | CG74: Y
A75: flow sensor เครื่อง drager. | B75: 12302 | C75: กล่อง | D75: 4 | E75: Y | O75: 7490 | V75: 1 | W75: 36 | Z75: MS-ME-06-0116 | AG75: 45865 | BA75: flow sensor เครื่อง drager. | BC75: 6 | BE75: flow sensor เครื่อง drager. | CG75: Y
A76: LMA (dispossible) no5.0 แบบตรง. | B76: 12393 | C76: ชิ้น | D76: 4 | E76: Y | O76: 0 | V76: 1 | W76: 36 | Z76: MS-ME-06-0154 | AG76: 45865 | BA76: LMA (dispossible) no5.0 แบบตรง. | BC76: 6 | BE76: LMA (dispossible) no5.0 แบบตรง. | CG76: Y
A77: LMA I-jel (for reuse)l No.1.0. | B77: 12394 | C77: อัน | D77: 4 | E77: Y | O77: 0 | V77: 1 | W77: 36 | Z77: MS-ME-06-0070 | AG77: 45865 | BA77: LMA I-jel (for reuse)l No.1.0. | BC77: 6 | BE77: LMA I-jel (for reuse)l No.1.0. | CG77: Y
A78: Odentoid screw (1 ชิ้น) | B78: 13142 | C78: ชิ้น | D78: 26 | E78: Y | O78: 12000 | V78: 1 | W78: 11 | Y78: 13261 | Z78: 004-06-163-003 | AG78: 45865 | BA78: Odentoid screw (1 ชิ้น) | BB78: 1 | BC78: 6 | BE78: Odentoid screw (1 ชิ้น) | BR78: 0 | CF78: 45924.653 | CG78: N
A79: Odentoid screw (2ชิ้น) | B79: 13143 | C79: ชุด | D79: 26 | E79: Y | O79: 0 | V79: 1 | W79: 11 | Z79: 004-06-163-004 | AG79: 45865 | BA79: Odentoid screw (2ชิ้น) | BB79: 1 | BC79: 6 | BE79: Odentoid screw (2ชิ้น) | CF79: 45924.653 | CG79: N
A80: ยูเนี่ยนพีวีซี ขนาด 1 นิ้ว | B80: 2646 | C80: อัน | D80: 3 | E80: Y | O80: 72 | V80: 1 | Y80: 87.5 | Z80: PI-0050630002 | AG80: 45865 | AJ80: 5 | BA80: ยูเนี่ยนพีวีซี ขนาด 1 นิ้ว | BC80: 19 | BE80: ยูเนี่ยนพีวีซี ขนาด 1 นิ้ว | BK80: 0 | BN80: 0 | CD80: 2025-12-22 18:16:07.628388 | CG80: Y
A81: Broad Curve LCP Stainless steel 5.0 | B81: 13139 | C81: ชิ้น | D81: 26 | E81: Y | O81: 15000 | V81: 1 | W81: 13 | Y81: 16561 | Z81: 004-02-176-022 | AG81: 45865 | BA81: Broad Curve LCP Stainless steel 5.0 | BB81: 1 | BC81: 6 | BE81: Broad Curve LCP Stainless steel 5.0 | BR81: 0 | CF81: 45950.458 | CG81: Y
A82: LCP Conical Ti 2.7/3.5 mm | B82: 13131 | C82: ชิ้น | D82: 26 | E82: Y | O82: 12200 | V82: 1 | W82: 13 | Y82: 13481 | Z82: 004-02-171-026 | AG82: 45865 | BA82: LCP Conical Ti 2.7/3.5 mm | BB82: 1 | BC82: 6 | BE82: LCP Conical Ti 2.7/3.5 mm | BR82: 0 | CF82: 45950.459 | CG82: Y
A83: Tuftex Over The Wire Embolectomy catheter | B83: 11723 | C83: ชิ้น | D83: 26 | E83: Y | O83: 5350 | V83: 1 | W83: 9 | Z83: 004-01-039-010 | AG83: 45865 | BA83: Tuftex Over The Wire Embolectomy catheter | BC83: 6 | BE83: Tuftex Over The Wire Embolectomy catheter | BL83: บริษัท เลอแม็ทร์ จำกัด | BM83: บริษัท เลอแม็ทร์ จำกัด | CG83: Y
A84: flexible ETT cuff no4.0. | B84: 12289 | C84: อัน | D84: 4 | E84: Y | O84: 0 | V84: 1 | W84: 36 | Z84: MS-ME-06-0056 | AG84: 45865 | BA84: flexible ETT cuff no4.0. | BC84: 6 | BE84: flexible ETT cuff no4.0. | CG84: Y
A85: flexible ETT uncuff no 3.5. | B85: 12290 | C85: อัน | D85: 4 | E85: Y | O85: 0 | V85: 1 | W85: 36 | Z85: MS-ME-06-0048 | AG85: 45865 | BA85: flexible ETT uncuff no 3.5. | BC85: 6 | BE85: flexible ETT uncuff no 3.5. | CG85: Y
A86: flexible ETT uncuff no 4.0. | B86: 12291 | C86: อัน | D86: 4 | E86: Y | O86: 0 | V86: 1 | W86: 36 | Z86: MS-ME-06-0049 | AG86: 45865 | BA86: flexible ETT uncuff no 4.0. | BC86: 6 | BE86: flexible ETT uncuff no 4.0. | CG86: Y
A87: Flexible ETT uncuff No.5.5. | B87: 12294 | C87: อัน | D87: 4 | E87: Y | O87: 0 | V87: 1 | W87: 36 | Z87: MS-ME-06-0052 | AG87: 45865 | BA87: Flexible ETT uncuff No.5.5. | BC87: 6 | BE87: Flexible ETT uncuff No.5.5. | CG87: Y
A88: flexible ETT uncuff no6.0. | B88: 12295 | C88: อัน | D88: 4 | E88: Y | O88: 0 | V88: 1 | W88: 36 | Z88: MS-ME-06-0053 | AG88: 45865 | BA88: flexible ETT uncuff no6.0. | BC88: 6 | BE88: flexible ETT uncuff no6.0. | CG88: Y
A89: flow sensor เครี่อง ohdema. | B89: 12301 | C89: อัน | D89: 4 | E89: Y | O89: 0 | V89: 1 | W89: 36 | Z89: MS-ME-06-0117 | AG89: 45865 | BA89: flow sensor เครี่อง ohdema. | BC89: 6 | BE89: flow sensor เครี่อง ohdema. | CG89: Y
A90: LMA I-jel (for reuse)No.2.5. | B90: 12397 | C90: อัน | D90: 4 | E90: Y | O90: 0 | V90: 1 | W90: 36 | Z90: MS-ME-06-0073 | AG90: 45865 | BA90: LMA I-jel (for reuse)No.2.5. | BC90: 6 | BE90: LMA I-jel (for reuse)No.2.5. | CG90: Y
A91: MAS-A-O3-sensor-Adult(เซนเซอร์วัดออกซิเจนในสมอง) | B91: 12419 | C91: ชุด | D91: 4 | E91: Y | O91: 3300 | V91: 1 | W91: 36 | Z91: MS-ME-06-0095 | AG91: 45865 | BA91: MAS-A-O3-sensor-Adult(เซนเซอร์วัดออกซิเจนในสมอง) | BC91: 6 | BE91: MAS-A-O3-sensor-Adult(เซนเซอร์วัดออกซิเจนในสมอง) | CG91: Y
A92: Tubing pump | B92: 11719 | C92: ชิ้น | D92: 26 | E92: Y | O92: 2500 | V92: 1 | W92: 9 | Z92: 004-02-092-008 | AG92: 45865 | BA92: Tubing pump | BC92: 6 | BE92: Tubing pump | CG92: Y
A93: Tunneler curve | B93: 11724 | C93: ชิ้น | D93: 26 | E93: Y | O93: 43200 | V93: 1 | W93: 17 | Z93: OR05-08-002-001 | AG93: 45865 | BA93: Tunneler curve | BC93: 6 | BE93: Tunneler curve | CG93: Y
A94: Twist drill 1.5x8 mm for midas Rex | B94: 11726 | C94: ชิ้น | D94: 26 | E94: Y | O94: 4500 | V94: 1 | W94: 11 | Z94: 004-06-166-007 | AG94: 45865 | BA94: Twist drill 1.5x8 mm for midas Rex | BC94: 6 | BE94: Twist drill 1.5x8 mm for midas Rex | CG94: Y
A95: MLT (microlaryngeal tube) No.4 | B95: 12433 | C95: อัน | D95: 4 | E95: Y | O95: 0 | V95: 1 | W95: 36 | Z95: MS-ME-06-0140 | AG95: 45865 | BA95: MLT (microlaryngeal tube) No.4 | BC95: 6 | BE95: MLT (microlaryngeal tube) No.4 | CG95: Y
A96: อาหารผู้ป่วย | B96: 4677 | C96: ชุด | D96: 18 | E96: Y | O96: 50 | V96: 1 | W96: 79 | Z96: NT-0060080046 | AG96: 45865 | BA96: อาหารผู้ป่วย | BB96: 1 | BC96: 10 | BE96: อาหารผู้ป่วย | BL96: นายนิกษา วงษ์ตาวัน | BM96: นายนิกษา วงษ์ตาวัน | CF96: 45854.468 | CG96: Y
A97: MLT (microlaryngeal tube) No.6 | B97: 12435 | C97: อัน | D97: 4 | E97: Y | O97: 0 | V97: 1 | W97: 36 | Z97: MS-ME-06-0141 | AG97: 45865 | BA97: MLT (microlaryngeal tube) No.6 | BC97: 6 | BE97: MLT (microlaryngeal tube) No.6 | CG97: Y
A98: Nasal RAE ETT uncuff No4.5. | B98: 12468 | C98: อัน | D98: 4 | E98: Y | O98: 0 | V98: 1 | W98: 36 | Z98: MS-ME-06-0043 | AG98: 45865 | BA98: Nasal RAE ETT uncuff No4.5. | BC98: 6 | BE98: Nasal RAE ETT uncuff No4.5. | CG98: Y
A99: Moisture Reponsive Catheter dressing (6cmx7cm) | B99: 12436 | C99: กล่อง | D99: 4 | E99: Y | O99: 588.5 | V99: 1 | W99: 36 | Z99: MS-ME-06-0153 | AG99: 45865 | BA99: Moisture Reponsive Catheter dressing (6cmx7cm) | BC99: 6 | BE99: Moisture Reponsive Catheter dressing (6cmx7cm) | CG99: Y
A100: Moisture Reponsive Catheter dressing (9cmx12cm) | B100: 12437 | C100: กล่อง | D100: 4 | E100: Y | O100: 1177 | V100: 1 | W100: 36 | Z100: MS-ME-06-0152 | AG100: 45865 | BA100: Moisture Reponsive Catheter dressing (9cmx12cm) | BC100: 6 | BE100: Moisture Reponsive Catheter dressing (9cmx12cm) | CG100: Y
...
